ctfdpy/__init__.py
ctfdpy/client.py
ctfdpy/exceptions.py
ctfdpy/utils.py
ctfdpy/api/__init__.py
ctfdpy/api/challenges.py
ctfdpy/api/files.py
ctfdpy/api/flags.py
ctfdpy/api/hints.py
ctfdpy/api/tags.py
ctfdpy/api/topics.py
ctfdpy/api/users.py
ctfdpy/auth/__init__.py
ctfdpy/auth/base.py
ctfdpy/auth/credentials.py
ctfdpy/auth/token.py
ctfdpy/auth/unauth.py
ctfdpy/models/__init__.py
ctfdpy/models/challenges.py
ctfdpy/models/files.py
ctfdpy/models/flags.py
ctfdpy/models/hints.py
ctfdpy/models/model.py
ctfdpy/models/tags.py
ctfdpy/models/topics.py
ctfdpy/models/users.py
ctfdpy/types/__init__.py
ctfdpy/types/api.py
ctfdpy/types/challenges.py
ctfdpy/types/files.py
ctfdpy/types/flags.py
ctfdpy/types/hints.py
ctfdpy-0.1.0a1.dist-info/METADATA
ctfdpy-0.1.0a1.dist-info/WHEEL
ctfdpy-0.1.0a1.dist-info/licenses/LICENSE
ctfdpy-0.1.0a1.dist-info/RECORD
